__init__.py
terraland/__init__.py
terraland/__version__.py
terraland/logo.py
terraland/settings.py
terraland/domain/__init__.py
terraland/domain/file_system/__init__.py
terraland/domain/file_system/entities.py
terraland/domain/file_system/exceptions.py
terraland/domain/file_system/services.py
terraland/domain/operation_system/__init__.py
terraland/domain/operation_system/entities.py
terraland/domain/operation_system/exceptions.py
terraland/domain/operation_system/services.py
terraland/domain/terraform/__init__.py
terraland/domain/terraform/common/__init__.py
terraland/domain/terraform/common/entities.py
terraland/domain/terraform/common/exceptions.py
terraland/domain/terraform/core/__init__.py
terraland/domain/terraform/core/entities.py
terraland/domain/terraform/core/exceptions.py
terraland/domain/terraform/core/services.py
terraland/domain/terraform/workspaces/__init__.py
terraland/domain/terraform/workspaces/entities.py
terraland/domain/terraform/workspaces/exceptions.py
terraland/domain/terraform/workspaces/services.py
terraland/infrastructure/__init__.py
terraland/infrastructure/file_system/__init__.py
terraland/infrastructure/file_system/exceptions.py
terraland/infrastructure/file_system/services.py
terraland/infrastructure/file_system/utils.py
terraland/infrastructure/operation_system/__init__.py
terraland/infrastructure/operation_system/exceptions.py
terraland/infrastructure/operation_system/services.py
terraland/infrastructure/shared/__init__.py
terraland/infrastructure/shared/command_process_context_manager.py
terraland/infrastructure/shared/command_utils.py
terraland/infrastructure/shared/exceptions.py
terraland/infrastructure/terraform/__init__.py
terraland/infrastructure/terraform/core/__init__.py
terraland/infrastructure/terraform/core/exceptions.py
terraland/infrastructure/terraform/core/services.py
terraland/infrastructure/terraform/core/command_builders/__init__.py
terraland-0.1.3.dist-info/METADATA
terraland-0.1.3.dist-info/WHEEL
terraland-0.1.3.dist-info/entry_points.txt
terraland-0.1.3.dist-info/licenses/LICENSE
terraland-0.1.3.dist-info/RECORD
