Metadata-Version: 2.4
Name: terraland
Version: 0.1.3
Dynamic: Requires-Dist
Summary: Terminal IDE for Terraform
Project-URL: Homepage, https://github.com/the-impact-craft/terraland
Project-URL: Issues, https://github.com/the-impact-craft/terraland/issues
Author-email: Bohdana Kuzmenko <bohdana.kuzmenko.dev@gmail.com>
License-File: LICENSE
Requires-Python: >=3.12
